rawbuilder/__init__.py
rawbuilder/rawbuilder.py
rawbuilder/schema.json
rawbuilder/schema.yml
rawbuilder/dataset/DataSet.py
rawbuilder/dataset/__init__.py
rawbuilder/factory/Factory.py
rawbuilder/factory/__init__.py
rawbuilder/mocker/Mocker.py
rawbuilder/mocker/__init__.py
rawbuilder-0.0.7.dist-info/AUTHORS.rst
rawbuilder-0.0.7.dist-info/LICENSE
rawbuilder-0.0.7.dist-info/METADATA
rawbuilder-0.0.7.dist-info/WHEEL
rawbuilder-0.0.7.dist-info/top_level.txt
rawbuilder-0.0.7.dist-info/RECORD
