Metadata-Version: 2.1
Name: rawbuilder
Version: 0.0.7
Summary: an elegant datasets factory
Home-page: https://github.com/M-Farag/rawbuilder
Author: Mina Farag Amin
Author-email: mina.farag@icloud.com
License: MIT license
Keywords: rawbuilder
Platform: UNKNOWN
Classifier: Development Status :: 2 - Pre-Alpha
Classifier: Intended Audience :: Developers
Classifier: License :: OSI Approved :: MIT License
Classifier: Natural Language :: English
Classifier: Programming Language :: Python :: 3
Classifier: Programming Language :: Python :: 3.6
Classifier: Programming Language :: Python :: 3.7
Classifier: Programming Language :: Python :: 3.8
Requires-Python: >=3.6
Requires-Dist: pandas
Requires-Dist: faker
Requires-Dist: numpy
